pybgpranking2/__init__.py
pybgpranking2/api.py
pybgpranking2/py.typed
pybgpranking2-2.0.2.dist-info/LICENSE
pybgpranking2-2.0.2.dist-info/METADATA
pybgpranking2-2.0.2.dist-info/WHEEL
pybgpranking2-2.0.2.dist-info/entry_points.txt
pybgpranking2-2.0.2.dist-info/RECORD
